{"ongoing_trials": {"tuner0": "02"}, "hyperparameters": {"space": [{"class_name": "Int", "config": {"name": "units", "default": null, "conditions": [], "min_value": 12, "max_value": 512, "step": 100, "sampling": "linear"}}, {"class_name": "Int", "config": {"name": "units_layer2", "default": null, "conditions": [], "min_value": 12, "max_value": 512, "step": 100, "sampling": "linear"}}, {"class_name": "Int", "config": {"name": "units_layer3", "default": null, "conditions": [], "min_value": 12, "max_value": 512, "step": 100, "sampling": "linear"}}, {"class_name": "Float", "config": {"name": "learning_rate", "default": 0.0001, "conditions": [], "min_value": 0.0001, "max_value": 0.01, "step": null, "sampling": "log"}}], "values": {"units": 12, "units_layer2": 12, "units_layer3": 12, "learning_rate": 0.0001}}, "start_order": ["00", "01", "02"], "end_order": ["00", "01"], "run_times": {"00": 1, "01": 1}, "retry_queue": [], "seed": 15, "seed_state": 15, "tried_so_far": ["7b7e1be35d40aa6eb28b281602f1e7f9", "0f3a3fff0b9599aa511b3fd8a650230e", "4fd6680c45eeea5d7e3268712fa55024"], "id_to_hash": {"00": "7b7e1be35d40aa6eb28b281602f1e7f9", "01": "0f3a3fff0b9599aa511b3fd8a650230e", "02": "4fd6680c45eeea5d7e3268712fa55024"}, "display": {"search_start": "2024-02-21T16:12:58.010997", "trial_start": {"00": "2024-02-21T16:12:58.010997", "01": "2024-02-21T16:14:02.786020"}, "trial_number": {"00": 1, "01": 2}}}